{"name":"build-javascript","namedChunkGroups":{"app":{"name":"app","assets":[{"name":"webpack-runtime-a7c90be945008f81faab.js","size":3528},{"name":"framework-d919716a71c0656db2d1.js","size":928},{"name":"app-67cb269c7fd60c59f475.js","size":218354}],"filteredAssets":0,"assetsSize":222810,"filteredAuxiliaryAssets":3,"auxiliaryAssetsSize":649607},"component---src-pages-404-tsx":{"name":"component---src-pages-404-tsx","assets":[{"name":"component---src-pages-404-tsx-ca3c8537c6398b095cf9.js","size":761}],"filteredAssets":0,"assetsSize":761,"filteredAuxiliaryAssets":1,"auxiliaryAssetsSize":1897},"component---src-pages-index-tsx":{"name":"component---src-pages-index-tsx","assets":[{"name":"component---src-pages-index-tsx-16b4d370ef1fe98093c0.js","size":4142}],"filteredAssets":0,"assetsSize":4142,"filteredAuxiliaryAssets":1,"auxiliaryAssetsSize":8327}},"assetsByChunkName":{"app":["webpack-runtime-a7c90be945008f81faab.js","framework-d919716a71c0656db2d1.js","app-67cb269c7fd60c59f475.js"],"component---src-pages-404-tsx":["component---src-pages-404-tsx-ca3c8537c6398b095cf9.js"],"component---src-pages-index-tsx":["component---src-pages-index-tsx-16b4d370ef1fe98093c0.js"]},"childAssetsByChunkName":{}}